{
  "ideal_client_profile": {
    "version": "1.0",
    "last_updated": "2026-04-06",

    "demographics": {
      "age_range": "25–45",
      "gender": "Женщины",
      "location": "Русскоязычные, по всему миру (Россия, СНГ, эмиграция)",
      "income_level": "Средний — могут позволить онлайн-терапию",
      "education": "Высшее или незаконченное высшее"
    },

    "psychographics": {
      "values": [
        "Честность с собой",
        "Глубина отношений",
        "Внутренний покой"
      ],
      "beliefs": [
        "Со мной что-то не так (ложное убеждение, которое мы мягко развенчиваем)",
        "Мне нужно разобраться в себе, чтобы отношения стали другими",
        "Терапия — это не слабость, а сила"
      ],
      "personality_traits": [
        "Чувствительные",
        "Склонные к рефлексии",
        "Тревожные, но осознанные"
      ]
    },

    "problems_and_pain_points": {
      "primary_problems": [
        {
          "problem": "Тревожная привязанность — цепляние, страх потери, потребность в постоянном подтверждении",
          "severity": "HIGH",
          "frequency": "Ежедневно в отношениях"
        },
        {
          "problem": "Потеря себя — в отношениях, после переезда, после абьюза",
          "severity": "HIGH",
          "frequency": "Фоновое состояние"
        },
        {
          "problem": "Незажившая травма — повторяющиеся паттерны, триггеры из прошлого",
          "severity": "HIGH",
          "frequency": "Циклично"
        }
      ],
      "frustrations": [
        "Устали чувствовать себя 'слишком' — слишком тревожными, нуждающимися, чувствительными",
        "Предыдущая терапия не помогла или была поверхностной",
        "Чувствуют, что их никто по-настоящему не понимает"
      ],
      "fears": [
        "Что я такая навсегда",
        "Что я не заслуживаю нормальных отношений",
        "Что терапия снова не поможет"
      ],
      "failed_solutions": [
        "Книги и статьи по психологии — понимают, но не меняется",
        "Попытки 'просто расслабиться' и 'отпустить'",
        "Короткосрочная терапия без работы с чувствами"
      ]
    },

    "goals_and_desires": {
      "immediate_goals": [
        "Перестать тревожиться в отношениях каждый день",
        "Понять что со мной происходит и почему"
      ],
      "long_term_aspirations": [
        "Чувствовать себя спокойно в отношениях",
        "Вернуть связь с собой",
        "Построить здоровые отношения"
      ],
      "dream_outcome": "Быть в отношениях и не терять себя. Чувствовать тревогу — и справляться."
    },

    "language_patterns": {
      "words_they_use": ["тревога", "привязанность", "контроль", "отпустить", "границы", "токсичный", "созависимость"],
      "phrases_they_say": [
        "Я всё понимаю головой, но ничего не могу с собой сделать",
        "Наверное, я слишком...",
        "Он ушёл, а я до сих пор жду",
        "Я не знаю, кто я без него"
      ],
      "questions_they_ask": [
        "Почему я снова выбираю таких?",
        "Как перестать тревожиться?",
        "Это вообще нормально — так чувствовать?"
      ]
    },

    "content_consumption": {
      "platforms": ["Instagram", "Telegram", "YouTube"],
      "content_formats": ["Короткие посты", "Reels", "Карусели"],
      "consumption_time": "Вечер, перед сном. Или в моменты тревоги.",
      "attention_span": "Короткий — сканируют, останавливаются на том, что резонирует"
    },

    "objections": {
      "common_objections": [
        {
          "objection": "Я уже была у психолога, не помогло",
          "response": "EFT работает не с головой, а с чувствами. Это другой процесс."
        },
        {
          "objection": "Онлайн-терапия не может быть настоящей",
          "response": "EFT работает с эмоциями, а они не зависят от расстояния."
        },
        {
          "objection": "Я боюсь, что станет хуже",
          "response": "Мы работаем так, чтобы касаться чувств без затопления. Вы в безопасности."
        }
      ]
    },

    "buying_triggers": {
      "emotional_triggers": [
        "Очередной болезненный цикл в отношениях",
        "Момент 'я больше так не могу'",
        "Прочитала пост и впервые почувствовала: меня понимают"
      ],
      "timing_triggers": [
        "После расставания",
        "После переезда / потери привычной среды",
        "В период обострения тревоги"
      ]
    }
  }
}
